{"cameraMode":{"drawMode":0,"name":"Shaded","section":"Shading Mode"},"sceneLighting":true,"audioPlay":false,"sceneViewState":{"showFog":true,"showMaterialUpdate":false,"showSkybox":true,"showFlares":true,"showImageEffects":true,"showParticleSystems":true},"in2DMode":false,"pivot":{"x":-7.542095184326172,"y":4.76769495010376,"z":1.5257339477539063},"rotation":{"x":-0.11149005591869354,"y":0.05602854862809181,"z":-0.006277202628552914,"w":-0.9921839833259583},"size":15.034002304077149,"orthographic":false}